grb/__init__.py
grb/attack/__init__.py
grb/attack/base.py
grb/attack/fgsm.py
grb/attack/pgd.py
grb/attack/rnd.py
grb/attack/speit.py
grb/attack/tdgia.py
grb/dataset/URLs.py
grb/dataset/__init__.py
grb/dataset/dataset.py
grb/defense/__init__.py
grb/defense/adv_trainer.py
grb/defense/base.py
grb/defense/gcnsvd.py
grb/defense/gnnguard.py
grb/defense/utils.py
grb/evaluator/__init__.py
grb/evaluator/evaluator.py
grb/evaluator/metric.py
grb/model/__init__.py
grb/model/cogdl/__init__.py
grb/model/dgl/__init__.py
grb/model/dgl/gat.py
grb/model/dgl/gcn.py
grb/model/dgl/gin.py
grb/model/dgl/grand.py
grb/model/torch/__init__.py
grb/model/torch/appnp.py
grb/model/torch/gcn.py
grb/model/torch/gin.py
grb/model/torch/graphsage.py
grb/model/torch/robustgcn.py
grb/model/torch/sgcn.py
grb/model/torch/tagcn.py
grb/utils/__init__.py
grb/utils/normalize.py
grb/utils/trainer.py
grb/utils/utils.py
grb/utils/visualize.py
tests/__init__.py
tests/context.py
tests/test_adv_train.py
tests/test_dataset.py
tests/test_model.py
grb-0.0.1.dist-info/LICENSE
grb-0.0.1.dist-info/METADATA
grb-0.0.1.dist-info/WHEEL
grb-0.0.1.dist-info/top_level.txt
grb-0.0.1.dist-info/RECORD
