Metadata-Version: 2.1
Name: grb
Version: 0.0.1
Summary: Graph Robustness Benchmark
Home-page: https://github.com/THUDM/grb
Author: Qinkai Zheng
Author-email: qinkai.zheng1028@gmail.com
License: MIT
Platform: UNKNOWN
Classifier: Development Status :: 3 - Alpha
Classifier: Intended Audience :: Science/Research
Classifier: Intended Audience :: Developers
Classifier: Topic :: Scientific/Engineering :: Artificial Intelligence
Classifier: License :: OSI Approved :: MIT License
Classifier: Programming Language :: Python :: 3
Classifier: Programming Language :: Python :: 3.6
Classifier: Programming Language :: Python :: 3.7
Classifier: Programming Language :: Python :: 3.8
Classifier: Operating System :: OS Independent
Requires-Dist: scipy
Requires-Dist: matplotlib
Requires-Dist: torch
Requires-Dist: numpy
Requires-Dist: networkx
Requires-Dist: recommonmark
Requires-Dist: pandas
Requires-Dist: cogdl
Requires-Dist: scikit-learn
